aws_config/__init__.py
aws_config/apps.py
aws_config/cli.py
aws_config/settings_handler.py
aws_config/utils.py
aws_config/wsgi.py
django_aws_config-0.0.0.dist-info/LICENSE
django_aws_config-0.0.0.dist-info/METADATA
django_aws_config-0.0.0.dist-info/WHEEL
django_aws_config-0.0.0.dist-info/top_level.txt
django_aws_config-0.0.0.dist-info/RECORD
