Metadata-Version: 2.1
Name: django-aws-config
Version: 0.0.0
Summary: A django package aimed to simplify payment integration into your application
Author-email: Trey <trey@strelix.org>
License: Apache License
Project-URL: Homepage, https://github.com/Strelix/django-aws-config
Project-URL: Issues, https://github.com/Strelix/django-aws-config/issues
Classifier: Environment :: Web Environment
Classifier: Framework :: Django
Classifier: Intended Audience :: Developers
Classifier: License :: OSI Approved :: BSD License
Classifier: Operating System :: OS Independent
Classifier: Programming Language :: Python
Classifier: Programming Language :: Python :: 3
Classifier: Programming Language :: Python :: 3 :: Only
Classifier: Programming Language :: Python :: 3.10
Classifier: Programming Language :: Python :: 3.11
Classifier: Programming Language :: Python :: 3.12
Requires-Python: >=3.10
License-File: LICENSE
Requires-Dist: Django >=3.2
